{
  "generated": "2026-06-21 05:30",
  "rooms": {
    "antimo": {
      "room": "Rhea's bedroom",
      "sensor": "Awair",
      "temp": 28,
      "rh": 59,
      "co2": 1728,
      "voc": 1298,
      "pm25": 17,
      "score": 46,
      "age_min": 10,
      "humidifier": {
        "on": false,
        "water_low": false,
        "rh": 62,
        "target": 60,
        "mode": "auto",
        "mist": 1
      }
    },
    "chiara": {
      "room": "Master bedroom",
      "sensor": "Vindstyrka",
      "temp": 27,
      "rh": 60,
      "voc": 136,
      "pm25": 3,
      "age_min": 10,
      "humidifier": {
        "on": false,
        "water_low": false,
        "rh": 55,
        "target": 60,
        "mode": "auto",
        "mist": 1
      }
    }
  }
}
