{
  "generated": "2026-06-22 02:30",
  "rooms": {
    "antimo": {
      "room": "Rhea's bedroom",
      "sensor": "Awair",
      "temp": 27,
      "rh": 59,
      "co2": 1524,
      "voc": 1364,
      "pm25": 82,
      "score": 48,
      "age_min": 10,
      "humidifier": {
        "on": true,
        "water_low": false,
        "rh": 60,
        "target": 60,
        "mode": "auto",
        "mist": 1
      }
    },
    "chiara": {
      "room": "Master bedroom",
      "sensor": "Vindstyrka",
      "temp": 25,
      "rh": 64,
      "voc": 137,
      "pm25": 18,
      "age_min": 10,
      "humidifier": {
        "on": true,
        "water_low": false,
        "rh": 55,
        "target": 60,
        "mode": "auto",
        "mist": 1
      }
    }
  }
}
