{
  "generated": "2026-06-26 07:00",
  "rooms": {
    "antimo": {
      "room": "Rhea's bedroom",
      "sensor": "Awair",
      "temp": 29,
      "rh": 55,
      "co2": 1326,
      "voc": 1299,
      "pm25": 6,
      "score": 61,
      "age_min": 10,
      "humidifier": {
        "on": false,
        "water_low": true,
        "rh": 61,
        "target": 60,
        "mode": "auto",
        "mist": 2
      }
    },
    "chiara": {
      "room": "Master bedroom",
      "sensor": "Vindstyrka",
      "temp": 29,
      "rh": 62,
      "voc": 199,
      "pm25": 7,
      "age_min": 10,
      "humidifier": {
        "on": false,
        "water_low": false,
        "rh": 59,
        "target": 60,
        "mode": "auto",
        "mist": 1
      }
    }
  }
}
